{
  "request": {
    "type": "userFunding",
    "user": "0xAf952a3543fea6B718f479E13E304F8f91440FCD",
    "startTime": 0
  },
  "response": [
    {
      "time": 1776556800000,
      "hash": "0x0000000000000000000000000000000000000000000000000000000000000000",
      "delta": {
        "type": "funding",
        "coin": "ETH",
        "usdc": "-0.002982",
        "szi": "-0.0924",
        "fundingRate": "-0.0000141816",
        "nSamples": 1
      }
    },
    {
      "time": 1776643200000,
      "hash": "0x0000000000000000000000000000000000000000000000000000000000000000",
      "delta": {
        "type": "funding",
        "coin": "BTC",
        "usdc": "0.001247",
        "szi": "0.0006825",
        "fundingRate": "-0.0000030016",
        "nSamples": 8
      }
    },
    {
      "time": 1776643200000,
      "hash": "0x0000000000000000000000000000000000000000000000000000000000000000",
      "delta": {
        "type": "funding",
        "coin": "ETH",
        "usdc": "0.006636",
        "szi": "0.0364428571",
        "fundingRate": "-0.0000111868",
        "nSamples": 7
      }
    },
    {
      "time": 1776643200000,
      "hash": "0x0000000000000000000000000000000000000000000000000000000000000000",
      "delta": {
        "type": "funding",
        "coin": "HYPE",
        "usdc": "0.045283",
        "szi": "-7.2707142857",
        "fundingRate": "0.0000107952",
        "nSamples": 14
      }
    },
    {
      "time": 1776643200000,
      "hash": "0x0000000000000000000000000000000000000000000000000000000000000000",
      "delta": {
        "type": "funding",
        "coin": "PAXG",
        "usdc": "-0.023146",
        "szi": "0.0175909091",
        "fundingRate": "0.0000125",
        "nSamples": 22
      }
    },
    {
      "time": 1776643200000,
      "hash": "0x0000000000000000000000000000000000000000000000000000000000000000",
      "delta": {
        "type": "funding",
        "coin": "SOL",
        "usdc": "-0.003271",
        "szi": "-0.4833333333",
        "fundingRate": "-0.0000134087",
        "nSamples": 6
      }
    },
    {
      "time": 1776643200000,
      "hash": "0x0000000000000000000000000000000000000000000000000000000000000000",
      "delta": {
        "type": "funding",
        "coin": "XRP",
        "usdc": "0.060603",
        "szi": "-482.2631578947",
        "fundingRate": "0.000004701",
        "nSamples": 19
      }
    },
    {
      "time": 1776643200000,
      "hash": "0x0000000000000000000000000000000000000000000000000000000000000000",
      "delta": {
        "type": "funding",
        "coin": "xyz:AAPL",
        "usdc": "0.00447",
        "szi": "-0.069",
        "fundingRate": "0.0000200453",
        "nSamples": 12
      }
    },
    {
      "time": 1776643200000,
      "hash": "0x0000000000000000000000000000000000000000000000000000000000000000",
      "delta": {
        "type": "funding",
        "coin": "xyz:AMD",
        "usdc": "0.005317",
        "szi": "-0.0999",
        "fundingRate": "0.0000193008",
        "nSamples": 10
      }
    },
    {
      "time": 1776643200000,
      "hash": "0x0000000000000000000000000000000000000000000000000000000000000000",
      "delta": {
        "type": "funding",
        "coin": "xyz:AMZN",
        "usdc": "0.000919",
        "szi": "-0.24",
        "fundingRate": "0.0000150401",
        "nSamples": 1
      }
    },
    {
      "time": 1776643200000,
      "hash": "0x0000000000000000000000000000000000000000000000000000000000000000",
      "delta": {
        "type": "funding",
        "coin": "xyz:BABA",
        "usdc": "0.002991",
        "szi": "-0.1035555556",
        "fundingRate": "0.0000229268",
        "nSamples": 9
      }
    },
    {
      "time": 1776643200000,
      "hash": "0x0000000000000000000000000000000000000000000000000000000000000000",
      "delta": {
        "type": "funding",
        "coin": "xyz:BRENTOIL",
        "usdc": "0.041234",
        "szi": "-0.975",
        "fundingRate": "0.0000783594",
        "nSamples": 6
      }
    },
    {
      "time": 1776643200000,
      "hash": "0x0000000000000000000000000000000000000000000000000000000000000000",
      "delta": {
        "type": "funding",
        "coin": "xyz:CL",
        "usdc": "0.00841",
        "szi": "-0.5832727273",
        "fundingRate": "0.0000149742",
        "nSamples": 11
      }
    },
    {
      "time": 1776643200000,
      "hash": "0x0000000000000000000000000000000000000000000000000000000000000000",
      "delta": {
        "type": "funding",
        "coin": "xyz:COPPER",
        "usdc": "0.006504",
        "szi": "-4.35",
        "fundingRate": "0.0000203688",
        "nSamples": 12
      }
    },
    {
      "time": 1776643200000,
      "hash": "0x0000000000000000000000000000000000000000000000000000000000000000",
      "delta": {
        "type": "funding",
        "coin": "xyz:CRCL",
        "usdc": "0.002082",
        "szi": "0.2955",
        "fundingRate": "-0.0000171954",
        "nSamples": 4
      }
    },
    {
      "time": 1776643200000,
      "hash": "0x0000000000000000000000000000000000000000000000000000000000000000",
      "delta": {
        "type": "funding",
        "coin": "xyz:CRWV",
        "usdc": "0.010893",
        "szi": "-0.1233333333",
        "fundingRate": "0.0000854331",
        "nSamples": 9
      }
    },
    {
      "time": 1776643200000,
      "hash": "0x0000000000000000000000000000000000000000000000000000000000000000",
      "delta": {
        "type": "funding",
        "coin": "xyz:EWY",
        "usdc": "0.098239",
        "szi": "-1.611625",
        "fundingRate": "0.0000170295",
        "nSamples": 24
      }
    },
    {
      "time": 1776643200000,
      "hash": "0x0000000000000000000000000000000000000000000000000000000000000000",
      "delta": {
        "type": "funding",
        "coin": "xyz:GOLD",
        "usdc": "0.006383",
        "szi": "-0.0139933333",
        "fundingRate": "0.0000063453",
        "nSamples": 15
      }
    },
    {
      "time": 1776643200000,
      "hash": "0x0000000000000000000000000000000000000000000000000000000000000000",
      "delta": {
        "type": "funding",
        "coin": "xyz:GOOGL",
        "usdc": "0.00021",
        "szi": "-0.03",
        "fundingRate": "0.0000207548",
        "nSamples": 1
      }
    },
    {
      "time": 1776643200000,
      "hash": "0x0000000000000000000000000000000000000000000000000000000000000000",
      "delta": {
        "type": "funding",
        "coin": "xyz:HOOD",
        "usdc": "0.000135",
        "szi": "-0.246",
        "fundingRate": "0.00000625",
        "nSamples": 1
      }
    },
    {
      "time": 1776643200000,
      "hash": "0x0000000000000000000000000000000000000000000000000000000000000000",
      "delta": {
        "type": "funding",
        "coin": "xyz:MU",
        "usdc": "0.003652",
        "szi": "-0.0522727273",
        "fundingRate": "0.0000141097",
        "nSamples": 11
      }
    },
    {
      "time": 1776643200000,
      "hash": "0x0000000000000000000000000000000000000000000000000000000000000000",
      "delta": {
        "type": "funding",
        "coin": "xyz:NFLX",
        "usdc": "0.000713",
        "szi": "-0.107",
        "fundingRate": "0.0000101162",
        "nSamples": 7
      }
    },
    {
      "time": 1776643200000,
      "hash": "0x0000000000000000000000000000000000000000000000000000000000000000",
      "delta": {
        "type": "funding",
        "coin": "xyz:NVDA",
        "usdc": "-0.001736",
        "szi": "0.1333333333",
        "fundingRate": "0.0000072905",
        "nSamples": 9
      }
    },
    {
      "time": 1776643200000,
      "hash": "0x0000000000000000000000000000000000000000000000000000000000000000",
      "delta": {
        "type": "funding",
        "coin": "xyz:ORCL",
        "usdc": "0.002897",
        "szi": "-0.1377142857",
        "fundingRate": "0.0000171446",
        "nSamples": 7
      }
    },
    {
      "time": 1776643200000,
      "hash": "0x0000000000000000000000000000000000000000000000000000000000000000",
      "delta": {
        "type": "funding",
        "coin": "xyz:SILVER",
        "usdc": "-0.00082",
        "szi": "-0.19",
        "fundingRate": "-0.0000067467",
        "nSamples": 8
      }
    },
    {
      "time": 1776643200000,
      "hash": "0x0000000000000000000000000000000000000000000000000000000000000000",
      "delta": {
        "type": "funding",
        "coin": "xyz:SNDK",
        "usdc": "-0.007098",
        "szi": "0.0199047619",
        "fundingRate": "0.0000189795",
        "nSamples": 21
      }
    },
    {
      "time": 1776643200000,
      "hash": "0x0000000000000000000000000000000000000000000000000000000000000000",
      "delta": {
        "type": "funding",
        "coin": "xyz:SP500",
        "usdc": "0.019365",
        "szi": "0.018125",
        "fundingRate": "-0.0000188515",
        "nSamples": 8
      }
    },
    {
      "time": 1776643200000,
      "hash": "0x0000000000000000000000000000000000000000000000000000000000000000",
      "delta": {
        "type": "funding",
        "coin": "xyz:TSLA",
        "usdc": "-0.000047",
        "szi": "0.0207777778",
        "fundingRate": "0.0000005902",
        "nSamples": 9
      }
    },
    {
      "time": 1776643200000,
      "hash": "0x0000000000000000000000000000000000000000000000000000000000000000",
      "delta": {
        "type": "funding",
        "coin": "xyz:TSM",
        "usdc": "0.001135",
        "szi": "0.0504",
        "fundingRate": "-0.0000123037",
        "nSamples": 5
      }
    },
    {
      "time": 1776643200000,
      "hash": "0x0000000000000000000000000000000000000000000000000000000000000000",
      "delta": {
        "type": "funding",
        "coin": "xyz:XYZ100",
        "usdc": "0.001558",
        "szi": "0.0009833333",
        "fundingRate": "-0.0000099729",
        "nSamples": 6
      }
    },
    {
      "time": 1776729600000,
      "hash": "0x0000000000000000000000000000000000000000000000000000000000000000",
      "delta": {
        "type": "funding",
        "coin": "BTC",
        "usdc": "-0.001601",
        "szi": "-0.0002163636",
        "fundingRate": "-0.0000088674",
        "nSamples": 11
      }
    },
    {
      "time": 1776729600000,
      "hash": "0x0000000000000000000000000000000000000000000000000000000000000000",
      "delta": {
        "type": "funding",
        "coin": "ETH",
        "usdc": "0.005178",
        "szi": "0.0286071429",
        "fundingRate": "-0.0000055844",
        "nSamples": 14
      }
    },
    {
      "time": 1776729600000,
      "hash": "0x0000000000000000000000000000000000000000000000000000000000000000",
      "delta": {
        "type": "funding",
        "coin": "HYPE",
        "usdc": "0.074171",
        "szi": "-14.5",
        "fundingRate": "0.0000125",
        "nSamples": 10
      }
    },
    {
      "time": 1776729600000,
      "hash": "0x0000000000000000000000000000000000000000000000000000000000000000",
      "delta": {
        "type": "funding",
        "coin": "PAXG",
        "usdc": "-0.003789",
        "szi": "0.0083333333",
        "fundingRate": "0.0000105553",
        "nSamples": 9
      }
    },
    {
      "time": 1776729600000,
      "hash": "0x0000000000000000000000000000000000000000000000000000000000000000",
      "delta": {
        "type": "funding",
        "coin": "SOL",
        "usdc": "0.005336",
        "szi": "6.2213636364",
        "fundingRate": "-0.0000004512",
        "nSamples": 22
      }
    },
    {
      "time": 1776729600000,
      "hash": "0x0000000000000000000000000000000000000000000000000000000000000000",
      "delta": {
        "type": "funding",
        "coin": "XRP",
        "usdc": "-0.011493",
        "szi": "76.0",
        "fundingRate": "0.0000087868",
        "nSamples": 12
      }
    },
    {
      "time": 1776729600000,
      "hash": "0x0000000000000000000000000000000000000000000000000000000000000000",
      "delta": {
        "type": "funding",
        "coin": "xyz:AAPL",
        "usdc": "0.000753",
        "szi": "-0.148",
        "fundingRate": "0.00000625",
        "nSamples": 3
      }
    },
    {
      "time": 1776729600000,
      "hash": "0x0000000000000000000000000000000000000000000000000000000000000000",
      "delta": {
        "type": "funding",
        "coin": "xyz:AMD",
        "usdc": "0.0016",
        "szi": "-0.037",
        "fundingRate": "0.0000142393",
        "nSamples": 11
      }
    },
    {
      "time": 1776729600000,
      "hash": "0x0000000000000000000000000000000000000000000000000000000000000000",
      "delta": {
        "type": "funding",
        "coin": "xyz:AMZN",
        "usdc": "0.068632",
        "szi": "-0.6368",
        "fundingRate": "0.0000211479",
        "nSamples": 20
      }
    },
    {
      "time": 1776729600000,
      "hash": "0x0000000000000000000000000000000000000000000000000000000000000000",
      "delta": {
        "type": "funding",
        "coin": "xyz:BABA",
        "usdc": "0.000407",
        "szi": "-0.071",
        "fundingRate": "0.0000204765",
        "nSamples": 2
      }
    },
    {
      "time": 1776729600000,
      "hash": "0x0000000000000000000000000000000000000000000000000000000000000000",
      "delta": {
        "type": "funding",
        "coin": "xyz:BRENTOIL",
        "usdc": "0.004763",
        "szi": "-1.066",
        "fundingRate": "0.0000095579",
        "nSamples": 5
      }
    },
    {
      "time": 1776729600000,
      "hash": "0x0000000000000000000000000000000000000000000000000000000000000000",
      "delta": {
        "type": "funding",
        "coin": "xyz:CL",
        "usdc": "0.002127",
        "szi": "-0.3511428571",
        "fundingRate": "0.0000099812",
        "nSamples": 7
      }
    },
    {
      "time": 1776729600000,
      "hash": "0x0000000000000000000000000000000000000000000000000000000000000000",
      "delta": {
        "type": "funding",
        "coin": "xyz:CRCL",
        "usdc": "-0.000141",
        "szi": "0.1155",
        "fundingRate": "0.00000625",
        "nSamples": 2
      }
    },
    {
      "time": 1776729600000,
      "hash": "0x0000000000000000000000000000000000000000000000000000000000000000",
      "delta": {
        "type": "funding",
        "coin": "xyz:CRWV",
        "usdc": "0.007968",
        "szi": "-0.164",
        "fundingRate": "0.0000836849",
        "nSamples": 5
      }
    },
    {
      "time": 1776729600000,
      "hash": "0x0000000000000000000000000000000000000000000000000000000000000000",
      "delta": {
        "type": "funding",
        "coin": "xyz:EWY",
        "usdc": "0.034916",
        "szi": "-0.8564",
        "fundingRate": "0.0000180376",
        "nSamples": 15
      }
    },
    {
      "time": 1776729600000,
      "hash": "0x0000000000000000000000000000000000000000000000000000000000000000",
      "delta": {
        "type": "funding",
        "coin": "xyz:GOLD",
        "usdc": "0.001952",
        "szi": "-0.00629",
        "fundingRate": "0.000006497",
        "nSamples": 10
      }
    },
    {
      "time": 1776729600000,
      "hash": "0x0000000000000000000000000000000000000000000000000000000000000000",
      "delta": {
        "type": "funding",
        "coin": "xyz:HOOD",
        "usdc": "0.005417",
        "szi": "-0.79075",
        "fundingRate": "0.0000197362",
        "nSamples": 4
      }
    },
    {
      "time": 1776729600000,
      "hash": "0x0000000000000000000000000000000000000000000000000000000000000000",
      "delta": {
        "type": "funding",
        "coin": "xyz:MU",
        "usdc": "-0.000046",
        "szi": "0.003",
        "fundingRate": "0.000005406",
        "nSamples": 6
      }
    },
    {
      "time": 1776729600000,
      "hash": "0x0000000000000000000000000000000000000000000000000000000000000000",
      "delta": {
        "type": "funding",
        "coin": "xyz:NFLX",
        "usdc": "0.000124",
        "szi": "-0.1075",
        "fundingRate": "0.00000625",
        "nSamples": 2
      }
    },
    {
      "time": 1776729600000,
      "hash": "0x0000000000000000000000000000000000000000000000000000000000000000",
      "delta": {
        "type": "funding",
        "coin": "xyz:ORCL",
        "usdc": "0.00838",
        "szi": "-0.2133333333",
        "fundingRate": "0.0000358125",
        "nSamples": 6
      }
    },
    {
      "time": 1776729600000,
      "hash": "0x0000000000000000000000000000000000000000000000000000000000000000",
      "delta": {
        "type": "funding",
        "coin": "xyz:PLTR",
        "usdc": "0.000063",
        "szi": "-0.069",
        "fundingRate": "0.00000625",
        "nSamples": 1
      }
    },
    {
      "time": 1776729600000,
      "hash": "0x0000000000000000000000000000000000000000000000000000000000000000",
      "delta": {
        "type": "funding",
        "coin": "xyz:RIVN",
        "usdc": "0.004649",
        "szi": "-0.885",
        "fundingRate": "0.0000509201",
        "nSamples": 6
      }
    },
    {
      "time": 1776729600000,
      "hash": "0x0000000000000000000000000000000000000000000000000000000000000000",
      "delta": {
        "type": "funding",
        "coin": "xyz:SILVER",
        "usdc": "0.002116",
        "szi": "-0.61",
        "fundingRate": "0.0000055765",
        "nSamples": 8
      }
    },
    {
      "time": 1776729600000,
      "hash": "0x0000000000000000000000000000000000000000000000000000000000000000",
      "delta": {
        "type": "funding",
        "coin": "xyz:SNDK",
        "usdc": "0.001898",
        "szi": "0.084",
        "fundingRate": "-0.0000248818",
        "nSamples": 1
      }
    },
    {
      "time": 1776729600000,
      "hash": "0x0000000000000000000000000000000000000000000000000000000000000000",
      "delta": {
        "type": "funding",
        "coin": "xyz:SP500",
        "usdc": "0.000401",
        "szi": "0.01225",
        "fundingRate": "-0.0000011597",
        "nSamples": 4
      }
    },
    {
      "time": 1776729600000,
      "hash": "0x0000000000000000000000000000000000000000000000000000000000000000",
      "delta": {
        "type": "funding",
        "coin": "xyz:TSLA",
        "usdc": "-0.000196",
        "szi": "0.05175",
        "fundingRate": "0.0000024229",
        "nSamples": 4
      }
    },
    {
      "time": 1776729600000,
      "hash": "0x0000000000000000000000000000000000000000000000000000000000000000",
      "delta": {
        "type": "funding",
        "coin": "xyz:XYZ100",
        "usdc": "-0.001163",
        "szi": "0.00145",
        "fundingRate": "0.0000037822",
        "nSamples": 8
      }
    },
    {
      "time": 1776816000000,
      "hash": "0x0000000000000000000000000000000000000000000000000000000000000000",
      "delta": {
        "type": "funding",
        "coin": "BTC",
        "usdc": "0.007508",
        "szi": "0.0005166667",
        "fundingRate": "-0.0000103778",
        "nSamples": 18
      }
    },
    {
      "time": 1776816000000,
      "hash": "0x0000000000000000000000000000000000000000000000000000000000000000",
      "delta": {
        "type": "funding",
        "coin": "ETH",
        "usdc": "-0.00019",
        "szi": "0.0086",
        "fundingRate": "0.0000093362",
        "nSamples": 1
      }
    },
    {
      "time": 1776816000000,
      "hash": "0x0000000000000000000000000000000000000000000000000000000000000000",
      "delta": {
        "type": "funding",
        "coin": "HYPE",
        "usdc": "0.000156",
        "szi": "-0.255",
        "fundingRate": "0.0000036903",
        "nSamples": 4
      }
    },
    {
      "time": 1776816000000,
      "hash": "0x0000000000000000000000000000000000000000000000000000000000000000",
      "delta": {
        "type": "funding",
        "coin": "PAXG",
        "usdc": "-0.04409",
        "szi": "0.0326086957",
        "fundingRate": "0.0000124303",
        "nSamples": 23
      }
    },
    {
      "time": 1776816000000,
      "hash": "0x0000000000000000000000000000000000000000000000000000000000000000",
      "delta": {
        "type": "funding",
        "coin": "SOL",
        "usdc": "-0.170318",
        "szi": "8.715",
        "fundingRate": "0.0000092894",
        "nSamples": 24
      }
    },
    {
      "time": 1776816000000,
      "hash": "0x0000000000000000000000000000000000000000000000000000000000000000",
      "delta": {
        "type": "funding",
        "coin": "XRP",
        "usdc": "-0.002378",
        "szi": "16.0",
        "fundingRate": "0.000011453",
        "nSamples": 9
      }
    },
    {
      "time": 1776816000000,
      "hash": "0x0000000000000000000000000000000000000000000000000000000000000000",
      "delta": {
        "type": "funding",
        "coin": "xyz:BRENTOIL",
        "usdc": "0.002952",
        "szi": "-0.7633333333",
        "fundingRate": "0.0000069019",
        "nSamples": 6
      }
    },
    {
      "time": 1776816000000,
      "hash": "0x0000000000000000000000000000000000000000000000000000000000000000",
      "delta": {
        "type": "funding",
        "coin": "xyz:CL",
        "usdc": "0.001655",
        "szi": "-0.814",
        "fundingRate": "0.0000075367",
        "nSamples": 3
      }
    },
    {
      "time": 1776816000000,
      "hash": "0x0000000000000000000000000000000000000000000000000000000000000000",
      "delta": {
        "type": "funding",
        "coin": "xyz:CRCL",
        "usdc": "0.00023",
        "szi": "-0.07475",
        "fundingRate": "0.0000077172",
        "nSamples": 4
      }
    },
    {
      "time": 1776816000000,
      "hash": "0x0000000000000000000000000000000000000000000000000000000000000000",
      "delta": {
        "type": "funding",
        "coin": "xyz:CRWV",
        "usdc": "0.0317",
        "szi": "-0.1733333333",
        "fundingRate": "0.0000727579",
        "nSamples": 21
      }
    },
    {
      "time": 1776816000000,
      "hash": "0x0000000000000000000000000000000000000000000000000000000000000000",
      "delta": {
        "type": "funding",
        "coin": "xyz:EWY",
        "usdc": "-0.004455",
        "szi": "0.222",
        "fundingRate": "0.0000099877",
        "nSamples": 13
      }
    },
    {
      "time": 1776816000000,
      "hash": "0x0000000000000000000000000000000000000000000000000000000000000000",
      "delta": {
        "type": "funding",
        "coin": "xyz:GOLD",
        "usdc": "0.072713",
        "szi": "-0.03485",
        "fundingRate": "0.0000244503",
        "nSamples": 18
      }
    },
    {
      "time": 1776816000000,
      "hash": "0x0000000000000000000000000000000000000000000000000000000000000000",
      "delta": {
        "type": "funding",
        "coin": "xyz:INTC",
        "usdc": "0.0001",
        "szi": "-0.12",
        "fundingRate": "0.00000625",
        "nSamples": 2
      }
    },
    {
      "time": 1776816000000,
      "hash": "0x0000000000000000000000000000000000000000000000000000000000000000",
      "delta": {
        "type": "funding",
        "coin": "xyz:META",
        "usdc": "0.000205",
        "szi": "-0.0245",
        "fundingRate": "0.00000625",
        "nSamples": 2
      }
    },
    {
      "time": 1776816000000,
      "hash": "0x0000000000000000000000000000000000000000000000000000000000000000",
      "delta": {
        "type": "funding",
        "coin": "xyz:MSFT",
        "usdc": "0.000286",
        "szi": "-0.0126",
        "fundingRate": "0.0000107773",
        "nSamples": 5
      }
    },
    {
      "time": 1776816000000,
      "hash": "0x0000000000000000000000000000000000000000000000000000000000000000",
      "delta": {
        "type": "funding",
        "coin": "xyz:NVDA",
        "usdc": "0.000644",
        "szi": "-0.057",
        "fundingRate": "0.00000625",
        "nSamples": 9
      }
    },
    {
      "time": 1776816000000,
      "hash": "0x0000000000000000000000000000000000000000000000000000000000000000",
      "delta": {
        "type": "funding",
        "coin": "xyz:ORCL",
        "usdc": "0.014443",
        "szi": "-0.2189230769",
        "fundingRate": "0.0000274806",
        "nSamples": 13
      }
    },
    {
      "time": 1776816000000,
      "hash": "0x0000000000000000000000000000000000000000000000000000000000000000",
      "delta": {
        "type": "funding",
        "coin": "xyz:RIVN",
        "usdc": "0.020026",
        "szi": "-0.4434782609",
        "fundingRate": "0.0001127621",
        "nSamples": 23
      }
    },
    {
      "time": 1776816000000,
      "hash": "0x0000000000000000000000000000000000000000000000000000000000000000",
      "delta": {
        "type": "funding",
        "coin": "xyz:SILVER",
        "usdc": "-0.000492",
        "szi": "-0.5383333333",
        "fundingRate": "-0.0000006152",
        "nSamples": 18
      }
    },
    {
      "time": 1776816000000,
      "hash": "0x0000000000000000000000000000000000000000000000000000000000000000",
      "delta": {
        "type": "funding",
        "coin": "xyz:SP500",
        "usdc": "0.001477",
        "szi": "0.0102142857",
        "fundingRate": "-0.000001453",
        "nSamples": 14
      }
    },
    {
      "time": 1776816000000,
      "hash": "0x0000000000000000000000000000000000000000000000000000000000000000",
      "delta": {
        "type": "funding",
        "coin": "xyz:XYZ100",
        "usdc": "0.000111",
        "szi": "0.0003",
        "fundingRate": "-0.0000046658",
        "nSamples": 3
      }
    },
    {
      "time": 1776902400000,
      "hash": "0x0000000000000000000000000000000000000000000000000000000000000000",
      "delta": {
        "type": "funding",
        "coin": "BTC",
        "usdc": "-0.002643",
        "szi": "0.00039",
        "fundingRate": "0.0000048403",
        "nSamples": 18
      }
    },
    {
      "time": 1776902400000,
      "hash": "0x0000000000000000000000000000000000000000000000000000000000000000",
      "delta": {
        "type": "funding",
        "coin": "HYPE",
        "usdc": "-0.000284",
        "szi": "-1.085",
        "fundingRate": "-0.0000031746",
        "nSamples": 2
      }
    },
    {
      "time": 1776902400000,
      "hash": "0x0000000000000000000000000000000000000000000000000000000000000000",
      "delta": {
        "type": "funding",
        "coin": "PAXG",
        "usdc": "-0.041905",
        "szi": "0.051",
        "fundingRate": "0.0000097033",
        "nSamples": 18
      }
    },
    {
      "time": 1776902400000,
      "hash": "0x0000000000000000000000000000000000000000000000000000000000000000",
      "delta": {
        "type": "funding",
        "coin": "SOL",
        "usdc": "-0.120192",
        "szi": "1.1886666667",
        "fundingRate": "0.0000784135",
        "nSamples": 15
      }
    },
    {
      "time": 1776902400000,
      "hash": "0x0000000000000000000000000000000000000000000000000000000000000000",
      "delta": {
        "type": "funding",
        "coin": "XRP",
        "usdc": "0.000631",
        "szi": "-13.0",
        "fundingRate": "0.0000056707",
        "nSamples": 6
      }
    },
    {
      "time": 1776902400000,
      "hash": "0x0000000000000000000000000000000000000000000000000000000000000000",
      "delta": {
        "type": "funding",
        "coin": "xyz:AAPL",
        "usdc": "-0.000063",
        "szi": "0.037",
        "fundingRate": "0.00000625",
        "nSamples": 1
      }
    },
    {
      "time": 1776902400000,
      "hash": "0x0000000000000000000000000000000000000000000000000000000000000000",
      "delta": {
        "type": "funding",
        "coin": "xyz:AMD",
        "usdc": "0.000577",
        "szi": "-0.0485",
        "fundingRate": "0.0000184265",
        "nSamples": 2
      }
    },
    {
      "time": 1776902400000,
      "hash": "0x0000000000000000000000000000000000000000000000000000000000000000",
      "delta": {
        "type": "funding",
        "coin": "xyz:AMZN",
        "usdc": "-0.00057",
        "szi": "0.072",
        "fundingRate": "0.00000625",
        "nSamples": 5
      }
    },
    {
      "time": 1776902400000,
      "hash": "0x0000000000000000000000000000000000000000000000000000000000000000",
      "delta": {
        "type": "funding",
        "coin": "xyz:BRENTOIL",
        "usdc": "0.000512",
        "szi": "0.05",
        "fundingRate": "-0.000034018",
        "nSamples": 3
      }
    },
    {
      "time": 1776902400000,
      "hash": "0x0000000000000000000000000000000000000000000000000000000000000000",
      "delta": {
        "type": "funding",
        "coin": "xyz:CL",
        "usdc": "-0.000241",
        "szi": "0.201",
        "fundingRate": "0.00000625",
        "nSamples": 2
      }
    },
    {
      "time": 1776902400000,
      "hash": "0x0000000000000000000000000000000000000000000000000000000000000000",
      "delta": {
        "type": "funding",
        "coin": "xyz:COIN",
        "usdc": "-0.000462",
        "szi": "0.075",
        "fundingRate": "0.00000625",
        "nSamples": 5
      }
    },
    {
      "time": 1776902400000,
      "hash": "0x0000000000000000000000000000000000000000000000000000000000000000",
      "delta": {
        "type": "funding",
        "coin": "xyz:COPPER",
        "usdc": "0.000766",
        "szi": "-2.73",
        "fundingRate": "0.0000230051",
        "nSamples": 2
      }
    },
    {
      "time": 1776902400000,
      "hash": "0x0000000000000000000000000000000000000000000000000000000000000000",
      "delta": {
        "type": "funding",
        "coin": "xyz:CRWV",
        "usdc": "0.013841",
        "szi": "-0.1736363636",
        "fundingRate": "0.0000299897",
        "nSamples": 22
      }
    },
    {
      "time": 1776902400000,
      "hash": "0x0000000000000000000000000000000000000000000000000000000000000000",
      "delta": {
        "type": "funding",
        "coin": "xyz:EWY",
        "usdc": "-0.001869",
        "szi": "0.264",
        "fundingRate": "0.0000114827",
        "nSamples": 4
      }
    },
    {
      "time": 1776902400000,
      "hash": "0x0000000000000000000000000000000000000000000000000000000000000000",
      "delta": {
        "type": "funding",
        "coin": "xyz:GOLD",
        "usdc": "0.058088",
        "szi": "-0.03959",
        "fundingRate": "0.0000155629",
        "nSamples": 20
      }
    },
    {
      "time": 1776902400000,
      "hash": "0x0000000000000000000000000000000000000000000000000000000000000000",
      "delta": {
        "type": "funding",
        "coin": "xyz:INTC",
        "usdc": "0.001492",
        "szi": "-0.1495",
        "fundingRate": "0.0000075397",
        "nSamples": 20
      }
    },
    {
      "time": 1776902400000,
      "hash": "0x0000000000000000000000000000000000000000000000000000000000000000",
      "delta": {
        "type": "funding",
        "coin": "xyz:MSFT",
        "usdc": "0.000064",
        "szi": "-0.025",
        "fundingRate": "0.00000625",
        "nSamples": 1
      }
    },
    {
      "time": 1776902400000,
      "hash": "0x0000000000000000000000000000000000000000000000000000000000000000",
      "delta": {
        "type": "funding",
        "coin": "xyz:MU",
        "usdc": "0.001448",
        "szi": "-0.02625",
        "fundingRate": "0.0000286034",
        "nSamples": 4
      }
    },
    {
      "time": 1776902400000,
      "hash": "0x0000000000000000000000000000000000000000000000000000000000000000",
      "delta": {
        "type": "funding",
        "coin": "xyz:NATGAS",
        "usdc": "0.000086",
        "szi": "-1.8",
        "fundingRate": "0.0000175777",
        "nSamples": 1
      }
    },
    {
      "time": 1776902400000,
      "hash": "0x0000000000000000000000000000000000000000000000000000000000000000",
      "delta": {
        "type": "funding",
        "coin": "xyz:NFLX",
        "usdc": "0.000499",
        "szi": "-0.216",
        "fundingRate": "0.00000625",
        "nSamples": 4
      }
    },
    {
      "time": 1776902400000,
      "hash": "0x0000000000000000000000000000000000000000000000000000000000000000",
      "delta": {
        "type": "funding",
        "coin": "xyz:NVDA",
        "usdc": "0.001312",
        "szi": "-0.0556111111",
        "fundingRate": "0.0000065583",
        "nSamples": 18
      }
    },
    {
      "time": 1776902400000,
      "hash": "0x0000000000000000000000000000000000000000000000000000000000000000",
      "delta": {
        "type": "funding",
        "coin": "xyz:ORCL",
        "usdc": "0.000044",
        "szi": "-0.033",
        "fundingRate": "0.0000076204",
        "nSamples": 1
      }
    },
    {
      "time": 1776902400000,
      "hash": "0x0000000000000000000000000000000000000000000000000000000000000000",
      "delta": {
        "type": "funding",
        "coin": "xyz:PLTR",
        "usdc": "0.000509",
        "szi": "-0.1915",
        "fundingRate": "0.000009365",
        "nSamples": 2
      }
    },
    {
      "time": 1776902400000,
      "hash": "0x0000000000000000000000000000000000000000000000000000000000000000",
      "delta": {
        "type": "funding",
        "coin": "xyz:RIVN",
        "usdc": "0.001981",
        "szi": "-0.24",
        "fundingRate": "0.0000199041",
        "nSamples": 24
      }
    },
    {
      "time": 1776902400000,
      "hash": "0x0000000000000000000000000000000000000000000000000000000000000000",
      "delta": {
        "type": "funding",
        "coin": "xyz:SILVER",
        "usdc": "0.00188",
        "szi": "-0.1556521739",
        "fundingRate": "0.0000069657",
        "nSamples": 23
      }
    },
    {
      "time": 1776902400000,
      "hash": "0x0000000000000000000000000000000000000000000000000000000000000000",
      "delta": {
        "type": "funding",
        "coin": "xyz:SP500",
        "usdc": "0.003502",
        "szi": "0.0063",
        "fundingRate": "-0.0000039173",
        "nSamples": 20
      }
    },
    {
      "time": 1776902400000,
      "hash": "0x0000000000000000000000000000000000000000000000000000000000000000",
      "delta": {
        "type": "funding",
        "coin": "xyz:TSLA",
        "usdc": "-0.000376",
        "szi": "0.081",
        "fundingRate": "0.00000625",
        "nSamples": 2
      }
    },
    {
      "time": 1776988800000,
      "hash": "0x0000000000000000000000000000000000000000000000000000000000000000",
      "delta": {
        "type": "funding",
        "coin": "BTC",
        "usdc": "0.026669",
        "szi": "-0.001576",
        "fundingRate": "0.0000108704",
        "nSamples": 20
      }
    },
    {
      "time": 1776988800000,
      "hash": "0x0000000000000000000000000000000000000000000000000000000000000000",
      "delta": {
        "type": "funding",
        "coin": "ETH",
        "usdc": "0.000041",
        "szi": "0.0044",
        "fundingRate": "-0.0000040588",
        "nSamples": 1
      }
    },
    {
      "time": 1776988800000,
      "hash": "0x0000000000000000000000000000000000000000000000000000000000000000",
      "delta": {
        "type": "funding",
        "coin": "HYPE",
        "usdc": "0.021262",
        "szi": "-8.236",
        "fundingRate": "0.0000125",
        "nSamples": 5
      }
    },
    {
      "time": 1776988800000,
      "hash": "0x0000000000000000000000000000000000000000000000000000000000000000",
      "delta": {
        "type": "funding",
        "coin": "PAXG",
        "usdc": "-0.004881",
        "szi": "0.0166",
        "fundingRate": "0.0000125",
        "nSamples": 5
      }
    },
    {
      "time": 1776988800000,
      "hash": "0x0000000000000000000000000000000000000000000000000000000000000000",
      "delta": {
        "type": "funding",
        "coin": "SOL",
        "usdc": "-0.035151",
        "szi": "-6.6372727273",
        "fundingRate": "-0.0000027702",
        "nSamples": 22
      }
    },
    {
      "time": 1776988800000,
      "hash": "0x0000000000000000000000000000000000000000000000000000000000000000",
      "delta": {
        "type": "funding",
        "coin": "XRP",
        "usdc": "0.004237",
        "szi": "-23.1818181818",
        "fundingRate": "0.0000057976",
        "nSamples": 22
      }
    },
    {
      "time": 1776988800000,
      "hash": "0x0000000000000000000000000000000000000000000000000000000000000000",
      "delta": {
        "type": "funding",
        "coin": "xyz:AAPL",
        "usdc": "-0.000124",
        "szi": "0.037",
        "fundingRate": "0.00000625",
        "nSamples": 2
      }
    },
    {
      "time": 1776988800000,
      "hash": "0x0000000000000000000000000000000000000000000000000000000000000000",
      "delta": {
        "type": "funding",
        "coin": "xyz:AMD",
        "usdc": "0.000088",
        "szi": "-0.029",
        "fundingRate": "0.0000087595",
        "nSamples": 1
      }
    },
    {
      "time": 1776988800000,
      "hash": "0x0000000000000000000000000000000000000000000000000000000000000000",
      "delta": {
        "type": "funding",
        "coin": "xyz:AMZN",
        "usdc": "-0.001397",
        "szi": "0.08",
        "fundingRate": "0.00000625",
        "nSamples": 11
      }
    },
    {
      "time": 1776988800000,
      "hash": "0x0000000000000000000000000000000000000000000000000000000000000000",
      "delta": {
        "type": "funding",
        "coin": "xyz:BABA",
        "usdc": "0.004755",
        "szi": "-0.0814375",
        "fundingRate": "0.0000272756",
        "nSamples": 16
      }
    },
    {
      "time": 1776988800000,
      "hash": "0x0000000000000000000000000000000000000000000000000000000000000000",
      "delta": {
        "type": "funding",
        "coin": "xyz:BRENTOIL",
        "usdc": "0.000883",
        "szi": "0.165",
        "fundingRate": "-0.0000133302",
        "nSamples": 4
      }
    },
    {
      "time": 1776988800000,
      "hash": "0x0000000000000000000000000000000000000000000000000000000000000000",
      "delta": {
        "type": "funding",
        "coin": "xyz:CL",
        "usdc": "0.000424",
        "szi": "-0.2135",
        "fundingRate": "0.0000104943",
        "nSamples": 2
      }
    },
    {
      "time": 1776988800000,
      "hash": "0x0000000000000000000000000000000000000000000000000000000000000000",
      "delta": {
        "type": "funding",
        "coin": "xyz:COIN",
        "usdc": "-0.000027",
        "szi": "0.022",
        "fundingRate": "0.00000625",
        "nSamples": 1
      }
    },
    {
      "time": 1776988800000,
      "hash": "0x0000000000000000000000000000000000000000000000000000000000000000",
      "delta": {
        "type": "funding",
        "coin": "xyz:COPPER",
        "usdc": "0.001824",
        "szi": "-3.7125",
        "fundingRate": "0.0000202022",
        "nSamples": 4
      }
    },
    {
      "time": 1776988800000,
      "hash": "0x0000000000000000000000000000000000000000000000000000000000000000",
      "delta": {
        "type": "funding",
        "coin": "xyz:CRCL",
        "usdc": "0.000083",
        "szi": "-0.04",
        "fundingRate": "0.0000209798",
        "nSamples": 1
      }
    },
    {
      "time": 1776988800000,
      "hash": "0x0000000000000000000000000000000000000000000000000000000000000000",
      "delta": {
        "type": "funding",
        "coin": "xyz:CRWV",
        "usdc": "0.002595",
        "szi": "-0.1",
        "fundingRate": "0.0000444683",
        "nSamples": 5
      }
    },
    {
      "time": 1776988800000,
      "hash": "0x0000000000000000000000000000000000000000000000000000000000000000",
      "delta": {
        "type": "funding",
        "coin": "xyz:EUR",
        "usdc": "0.000972",
        "szi": "-77.4",
        "fundingRate": "0.0000011993",
        "nSamples": 9
      }
    },
    {
      "time": 1776988800000,
      "hash": "0x0000000000000000000000000000000000000000000000000000000000000000",
      "delta": {
        "type": "funding",
        "coin": "xyz:EWJ",
        "usdc": "0.002073",
        "szi": "-0.244375",
        "fundingRate": "0.0000122094",
        "nSamples": 8
      }
    },
    {
      "time": 1776988800000,
      "hash": "0x0000000000000000000000000000000000000000000000000000000000000000",
      "delta": {
        "type": "funding",
        "coin": "xyz:GOLD",
        "usdc": "0.016914",
        "szi": "-0.0172863636",
        "fundingRate": "0.0000094667",
        "nSamples": 22
      }
    },
    {
      "time": 1776988800000,
      "hash": "0x0000000000000000000000000000000000000000000000000000000000000000",
      "delta": {
        "type": "funding",
        "coin": "xyz:HOOD",
        "usdc": "-0.000064",
        "szi": "0.041",
        "fundingRate": "0.00000625",
        "nSamples": 3
      }
    },
    {
      "time": 1776988800000,
      "hash": "0x0000000000000000000000000000000000000000000000000000000000000000",
      "delta": {
        "type": "funding",
        "coin": "xyz:MSTR",
        "usdc": "0.000575",
        "szi": "0.1573333333",
        "fundingRate": "-0.0000071243",
        "nSamples": 3
      }
    },
    {
      "time": 1776988800000,
      "hash": "0x0000000000000000000000000000000000000000000000000000000000000000",
      "delta": {
        "type": "funding",
        "coin": "xyz:MU",
        "usdc": "0.011325",
        "szi": "-0.0412941176",
        "fundingRate": "0.0000331468",
        "nSamples": 17
      }
    },
    {
      "time": 1776988800000,
      "hash": "0x0000000000000000000000000000000000000000000000000000000000000000",
      "delta": {
        "type": "funding",
        "coin": "xyz:NFLX",
        "usdc": "0.000251",
        "szi": "-0.218",
        "fundingRate": "0.00000625",
        "nSamples": 2
      }
    },
    {
      "time": 1776988800000,
      "hash": "0x0000000000000000000000000000000000000000000000000000000000000000",
      "delta": {
        "type": "funding",
        "coin": "xyz:NVDA",
        "usdc": "0.000193",
        "szi": "-0.099",
        "fundingRate": "0.0000093355",
        "nSamples": 1
      }
    },
    {
      "time": 1776988800000,
      "hash": "0x0000000000000000000000000000000000000000000000000000000000000000",
      "delta": {
        "type": "funding",
        "coin": "xyz:ORCL",
        "usdc": "0.000905",
        "szi": "-0.0562222222",
        "fundingRate": "0.0000101745",
        "nSamples": 9
      }
    },
    {
      "time": 1776988800000,
      "hash": "0x0000000000000000000000000000000000000000000000000000000000000000",
      "delta": {
        "type": "funding",
        "coin": "xyz:PLTR",
        "usdc": "0.000322",
        "szi": "-0.0953333333",
        "fundingRate": "0.0000079185",
        "nSamples": 3
      }
    },
    {
      "time": 1776988800000,
      "hash": "0x0000000000000000000000000000000000000000000000000000000000000000",
      "delta": {
        "type": "funding",
        "coin": "xyz:RIVN",
        "usdc": "0.002108",
        "szi": "-0.24",
        "fundingRate": "0.0000239354",
        "nSamples": 22
      }
    },
    {
      "time": 1776988800000,
      "hash": "0x0000000000000000000000000000000000000000000000000000000000000000",
      "delta": {
        "type": "funding",
        "coin": "xyz:SILVER",
        "usdc": "0.000256",
        "szi": "-0.0194117647",
        "fundingRate": "0.0000106002",
        "nSamples": 17
      }
    },
    {
      "time": 1776988800000,
      "hash": "0x0000000000000000000000000000000000000000000000000000000000000000",
      "delta": {
        "type": "funding",
        "coin": "xyz:SNDK",
        "usdc": "0.004545",
        "szi": "-0.0003333333",
        "fundingRate": "0.0047988389",
        "nSamples": 3
      }
    },
    {
      "time": 1776988800000,
      "hash": "0x0000000000000000000000000000000000000000000000000000000000000000",
      "delta": {
        "type": "funding",
        "coin": "xyz:SP500",
        "usdc": "0.002668",
        "szi": "0.005125",
        "fundingRate": "-0.0000045755",
        "nSamples": 16
      }
    },
    {
      "time": 1776988800000,
      "hash": "0x0000000000000000000000000000000000000000000000000000000000000000",
      "delta": {
        "type": "funding",
        "coin": "xyz:TSLA",
        "usdc": "0.000645",
        "szi": "0.0604",
        "fundingRate": "-0.0000056949",
        "nSamples": 5
      }
    },
    {
      "time": 1776988800000,
      "hash": "0x0000000000000000000000000000000000000000000000000000000000000000",
      "delta": {
        "type": "funding",
        "coin": "xyz:TSM",
        "usdc": "0.000833",
        "szi": "0.026",
        "fundingRate": "-0.0000063866",
        "nSamples": 13
      }
    },
    {
      "time": 1776988800000,
      "hash": "0x0000000000000000000000000000000000000000000000000000000000000000",
      "delta": {
        "type": "funding",
        "coin": "xyz:XYZ100",
        "usdc": "0.001592",
        "szi": "0.0015705882",
        "fundingRate": "-0.0000022039",
        "nSamples": 17
      }
    },
    {
      "time": 1777867200014,
      "hash": "0x0000000000000000000000000000000000000000000000000000000000000000",
      "delta": {
        "type": "funding",
        "coin": "XRP",
        "usdc": "0.000317",
        "szi": "-18.0",
        "fundingRate": "0.0000125",
        "nSamples": null
      }
    },
    {
      "time": 1777870800025,
      "hash": "0x0000000000000000000000000000000000000000000000000000000000000000",
      "delta": {
        "type": "funding",
        "coin": "XRP",
        "usdc": "-0.026068",
        "szi": "1724.0",
        "fundingRate": "0.0000106763",
        "nSamples": null
      }
    },
    {
      "time": 1777874400035,
      "hash": "0x0000000000000000000000000000000000000000000000000000000000000000",
      "delta": {
        "type": "funding",
        "coin": "XRP",
        "usdc": "0.000012",
        "szi": "-28.0",
        "fundingRate": "0.0000003164",
        "nSamples": null
      }
    },
    {
      "time": 1777881600065,
      "hash": "0x0000000000000000000000000000000000000000000000000000000000000000",
      "delta": {
        "type": "funding",
        "coin": "XRP",
        "usdc": "0.000081",
        "szi": "-55.0",
        "fundingRate": "0.0000010444",
        "nSamples": null
      }
    },
    {
      "time": 1777885200015,
      "hash": "0x0000000000000000000000000000000000000000000000000000000000000000",
      "delta": {
        "type": "funding",
        "coin": "XRP",
        "usdc": "-0.000303",
        "szi": "112.0",
        "fundingRate": "0.0000019227",
        "nSamples": null
      }
    },
    {
      "time": 1777888800011,
      "hash": "0x0000000000000000000000000000000000000000000000000000000000000000",
      "delta": {
        "type": "funding",
        "coin": "XRP",
        "usdc": "-0.001389",
        "szi": "136.0",
        "fundingRate": "0.000007206",
        "nSamples": null
      }
    },
    {
      "time": 1777892400065,
      "hash": "0x0000000000000000000000000000000000000000000000000000000000000000",
      "delta": {
        "type": "funding",
        "coin": "XRP",
        "usdc": "0.003001",
        "szi": "176.0",
        "fundingRate": "-0.0000122234",
        "nSamples": null
      }
    },
    {
      "time": 1777896000066,
      "hash": "0x0000000000000000000000000000000000000000000000000000000000000000",
      "delta": {
        "type": "funding",
        "coin": "XRP",
        "usdc": "0.028978",
        "szi": "1707.0",
        "fundingRate": "-0.0000121772",
        "nSamples": null
      }
    },
    {
      "time": 1777899600032,
      "hash": "0x0000000000000000000000000000000000000000000000000000000000000000",
      "delta": {
        "type": "funding",
        "coin": "XRP",
        "usdc": "0.019719",
        "szi": "1815.0",
        "fundingRate": "-0.0000077962",
        "nSamples": null
      }
    },
    {
      "time": 1777903200079,
      "hash": "0x0000000000000000000000000000000000000000000000000000000000000000",
      "delta": {
        "type": "funding",
        "coin": "XRP",
        "usdc": "0.024357",
        "szi": "1872.0",
        "fundingRate": "-0.0000093372",
        "nSamples": null
      }
    },
    {
      "time": 1777906800062,
      "hash": "0x0000000000000000000000000000000000000000000000000000000000000000",
      "delta": {
        "type": "funding",
        "coin": "XRP",
        "usdc": "-0.000006",
        "szi": "-1.0",
        "fundingRate": "-0.0000044093",
        "nSamples": null
      }
    },
    {
      "time": 1777917600053,
      "hash": "0x0000000000000000000000000000000000000000000000000000000000000000",
      "delta": {
        "type": "funding",
        "coin": "XRP",
        "usdc": "-0.0001",
        "szi": "-10.0",
        "fundingRate": "-0.0000071241",
        "nSamples": null
      }
    },
    {
      "time": 1777921200037,
      "hash": "0x0000000000000000000000000000000000000000000000000000000000000000",
      "delta": {
        "type": "funding",
        "coin": "XRP",
        "usdc": "0.000157",
        "szi": "-27.0",
        "fundingRate": "0.0000041539",
        "nSamples": null
      }
    },
    {
      "time": 1777932000075,
      "hash": "0x0000000000000000000000000000000000000000000000000000000000000000",
      "delta": {
        "type": "funding",
        "coin": "XRP",
        "usdc": "-0.000118",
        "szi": "-29.0",
        "fundingRate": "-0.0000029221",
        "nSamples": null
      }
    },
    {
      "time": 1777935600055,
      "hash": "0x0000000000000000000000000000000000000000000000000000000000000000",
      "delta": {
        "type": "funding",
        "coin": "XRP",
        "usdc": "0.000006",
        "szi": "-28.0",
        "fundingRate": "0.0000001768",
        "nSamples": null
      }
    },
    {
      "time": 1777953600016,
      "hash": "0x0000000000000000000000000000000000000000000000000000000000000000",
      "delta": {
        "type": "funding",
        "coin": "XRP",
        "usdc": "0.000105",
        "szi": "-15.0",
        "fundingRate": "0.0000049824",
        "nSamples": null
      }
    },
    {
      "time": 1777957200057,
      "hash": "0x0000000000000000000000000000000000000000000000000000000000000000",
      "delta": {
        "type": "funding",
        "coin": "XRP",
        "usdc": "0.000008",
        "szi": "-2.0",
        "fundingRate": "0.0000031548",
        "nSamples": null
      }
    },
    {
      "time": 1777971600016,
      "hash": "0x0000000000000000000000000000000000000000000000000000000000000000",
      "delta": {
        "type": "funding",
        "coin": "XRP",
        "usdc": "0.000703",
        "szi": "-40.0",
        "fundingRate": "0.0000125",
        "nSamples": null
      }
    },
    {
      "time": 1777978800054,
      "hash": "0x0000000000000000000000000000000000000000000000000000000000000000",
      "delta": {
        "type": "funding",
        "coin": "XRP",
        "usdc": "0.001089",
        "szi": "-62.0",
        "fundingRate": "0.0000125",
        "nSamples": null
      }
    },
    {
      "time": 1777982400025,
      "hash": "0x0000000000000000000000000000000000000000000000000000000000000000",
      "delta": {
        "type": "funding",
        "coin": "XRP",
        "usdc": "0.000527",
        "szi": "-30.0",
        "fundingRate": "0.0000125",
        "nSamples": null
      }
    },
    {
      "time": 1777986000065,
      "hash": "0x0000000000000000000000000000000000000000000000000000000000000000",
      "delta": {
        "type": "funding",
        "coin": "XRP",
        "usdc": "0.000494",
        "szi": "-28.0",
        "fundingRate": "0.0000125",
        "nSamples": null
      }
    },
    {
      "time": 1778007600036,
      "hash": "0x0000000000000000000000000000000000000000000000000000000000000000",
      "delta": {
        "type": "funding",
        "coin": "XRP",
        "usdc": "0.000015",
        "szi": "-2.0",
        "fundingRate": "0.0000053991",
        "nSamples": null
      }
    },
    {
      "time": 1778011200001,
      "hash": "0x0000000000000000000000000000000000000000000000000000000000000000",
      "delta": {
        "type": "funding",
        "coin": "XRP",
        "usdc": "0.00012",
        "szi": "-28.0",
        "fundingRate": "0.0000030438",
        "nSamples": null
      }
    },
    {
      "time": 1778029200002,
      "hash": "0x0000000000000000000000000000000000000000000000000000000000000000",
      "delta": {
        "type": "funding",
        "coin": "XRP",
        "usdc": "0.000188",
        "szi": "-25.0",
        "fundingRate": "0.0000053439",
        "nSamples": null
      }
    },
    {
      "time": 1778036400061,
      "hash": "0x0000000000000000000000000000000000000000000000000000000000000000",
      "delta": {
        "type": "funding",
        "coin": "XRP",
        "usdc": "0.000049",
        "szi": "-48.0",
        "fundingRate": "0.0000007252",
        "nSamples": null
      }
    },
    {
      "time": 1778047200051,
      "hash": "0x0000000000000000000000000000000000000000000000000000000000000000",
      "delta": {
        "type": "funding",
        "coin": "XRP",
        "usdc": "0.000257",
        "szi": "-20.0",
        "fundingRate": "0.0000090599",
        "nSamples": null
      }
    },
    {
      "time": 1778054400014,
      "hash": "0x0000000000000000000000000000000000000000000000000000000000000000",
      "delta": {
        "type": "funding",
        "coin": "XRP",
        "usdc": "0.000107",
        "szi": "-6.0",
        "fundingRate": "0.0000125",
        "nSamples": null
      }
    },
    {
      "time": 1778061600058,
      "hash": "0x0000000000000000000000000000000000000000000000000000000000000000",
      "delta": {
        "type": "funding",
        "coin": "XRP",
        "usdc": "0.001068",
        "szi": "-59.0",
        "fundingRate": "0.0000125",
        "nSamples": null
      }
    },
    {
      "time": 1778068800046,
      "hash": "0x0000000000000000000000000000000000000000000000000000000000000000",
      "delta": {
        "type": "funding",
        "coin": "XRP",
        "usdc": "0.000018",
        "szi": "-1.0",
        "fundingRate": "0.0000125",
        "nSamples": null
      }
    },
    {
      "time": 1778083200063,
      "hash": "0x0000000000000000000000000000000000000000000000000000000000000000",
      "delta": {
        "type": "funding",
        "coin": "XRP",
        "usdc": "-0.000076",
        "szi": "-13.0",
        "fundingRate": "-0.0000040913",
        "nSamples": null
      }
    },
    {
      "time": 1778086800019,
      "hash": "0x0000000000000000000000000000000000000000000000000000000000000000",
      "delta": {
        "type": "funding",
        "coin": "XRP",
        "usdc": "-0.000024",
        "szi": "-5.0",
        "fundingRate": "-0.0000034138",
        "nSamples": null
      }
    },
    {
      "time": 1778097600077,
      "hash": "0x0000000000000000000000000000000000000000000000000000000000000000",
      "delta": {
        "type": "funding",
        "coin": "XRP",
        "usdc": "-0.000883",
        "szi": "-58.0",
        "fundingRate": "-0.0000106623",
        "nSamples": null
      }
    },
    {
      "time": 1778104800045,
      "hash": "0x0000000000000000000000000000000000000000000000000000000000000000",
      "delta": {
        "type": "funding",
        "coin": "XRP",
        "usdc": "-0.00015",
        "szi": "-9.0",
        "fundingRate": "-0.0000117337",
        "nSamples": null
      }
    },
    {
      "time": 1778112000059,
      "hash": "0x0000000000000000000000000000000000000000000000000000000000000000",
      "delta": {
        "type": "funding",
        "coin": "XRP",
        "usdc": "-0.001105",
        "szi": "-47.0",
        "fundingRate": "-0.0000165116",
        "nSamples": null
      }
    },
    {
      "time": 1778140800060,
      "hash": "0x0000000000000000000000000000000000000000000000000000000000000000",
      "delta": {
        "type": "funding",
        "coin": "XRP",
        "usdc": "-0.001212",
        "szi": "-82.0",
        "fundingRate": "-0.0000104163",
        "nSamples": null
      }
    },
    {
      "time": 1778151600037,
      "hash": "0x0000000000000000000000000000000000000000000000000000000000000000",
      "delta": {
        "type": "funding",
        "coin": "XRP",
        "usdc": "-0.000424",
        "szi": "-40.0",
        "fundingRate": "-0.0000075186",
        "nSamples": null
      }
    },
    {
      "time": 1778155200009,
      "hash": "0x0000000000000000000000000000000000000000000000000000000000000000",
      "delta": {
        "type": "funding",
        "coin": "XRP",
        "usdc": "0.00003",
        "szi": "-7.0",
        "fundingRate": "0.0000030408",
        "nSamples": null
      }
    },
    {
      "time": 1778158800041,
      "hash": "0x0000000000000000000000000000000000000000000000000000000000000000",
      "delta": {
        "type": "funding",
        "coin": "XRP",
        "usdc": "-0.000265",
        "szi": "-41.0",
        "fundingRate": "-0.0000045855",
        "nSamples": null
      }
    },
    {
      "time": 1778166000021,
      "hash": "0x0000000000000000000000000000000000000000000000000000000000000000",
      "delta": {
        "type": "funding",
        "coin": "XRP",
        "usdc": "-0.000031",
        "szi": "-3.0",
        "fundingRate": "-0.0000076458",
        "nSamples": null
      }
    },
    {
      "time": 1778169600044,
      "hash": "0x0000000000000000000000000000000000000000000000000000000000000000",
      "delta": {
        "type": "funding",
        "coin": "XRP",
        "usdc": "0.000349",
        "szi": "-54.0",
        "fundingRate": "0.0000046574",
        "nSamples": null
      }
    },
    {
      "time": 1778173200070,
      "hash": "0x0000000000000000000000000000000000000000000000000000000000000000",
      "delta": {
        "type": "funding",
        "coin": "XRP",
        "usdc": "0.000008",
        "szi": "-11.0",
        "fundingRate": "0.0000005841",
        "nSamples": null
      }
    },
    {
      "time": 1778191200025,
      "hash": "0x0000000000000000000000000000000000000000000000000000000000000000",
      "delta": {
        "type": "funding",
        "coin": "XRP",
        "usdc": "0.000064",
        "szi": "-22.0",
        "fundingRate": "0.0000021185",
        "nSamples": null
      }
    },
    {
      "time": 1778202000002,
      "hash": "0x0000000000000000000000000000000000000000000000000000000000000000",
      "delta": {
        "type": "funding",
        "coin": "XRP",
        "usdc": "0.000163",
        "szi": "-29.0",
        "fundingRate": "0.0000040728",
        "nSamples": null
      }
    },
    {
      "time": 1778205600026,
      "hash": "0x0000000000000000000000000000000000000000000000000000000000000000",
      "delta": {
        "type": "funding",
        "coin": "XRP",
        "usdc": "-0.000235",
        "szi": "-57.0",
        "fundingRate": "-0.0000029793",
        "nSamples": null
      }
    },
    {
      "time": 1778223600012,
      "hash": "0x0000000000000000000000000000000000000000000000000000000000000000",
      "delta": {
        "type": "funding",
        "coin": "XRP",
        "usdc": "0.000111",
        "szi": "-41.0",
        "fundingRate": "0.0000019605",
        "nSamples": null
      }
    },
    {
      "time": 1778227200002,
      "hash": "0x0000000000000000000000000000000000000000000000000000000000000000",
      "delta": {
        "type": "funding",
        "coin": "XRP",
        "usdc": "0.000661",
        "szi": "-83.0",
        "fundingRate": "0.0000057625",
        "nSamples": null
      }
    },
    {
      "time": 1778234400074,
      "hash": "0x0000000000000000000000000000000000000000000000000000000000000000",
      "delta": {
        "type": "funding",
        "coin": "XRP",
        "usdc": "0.000064",
        "szi": "-12.0",
        "fundingRate": "0.0000038916",
        "nSamples": null
      }
    },
    {
      "time": 1778238000003,
      "hash": "0x0000000000000000000000000000000000000000000000000000000000000000",
      "delta": {
        "type": "funding",
        "coin": "XRP",
        "usdc": "0.000205",
        "szi": "-59.0",
        "fundingRate": "0.0000025031",
        "nSamples": null
      }
    },
    {
      "time": 1778241600055,
      "hash": "0x0000000000000000000000000000000000000000000000000000000000000000",
      "delta": {
        "type": "funding",
        "coin": "XRP",
        "usdc": "0.000123",
        "szi": "-40.0",
        "fundingRate": "0.000002224",
        "nSamples": null
      }
    },
    {
      "time": 1778245200029,
      "hash": "0x0000000000000000000000000000000000000000000000000000000000000000",
      "delta": {
        "type": "funding",
        "coin": "XRP",
        "usdc": "0.000069",
        "szi": "-22.0",
        "fundingRate": "0.0000022745",
        "nSamples": null
      }
    },
    {
      "time": 1778252400064,
      "hash": "0x0000000000000000000000000000000000000000000000000000000000000000",
      "delta": {
        "type": "funding",
        "coin": "XRP",
        "usdc": "0.000041",
        "szi": "-13.0",
        "fundingRate": "0.0000023055",
        "nSamples": null
      }
    },
    {
      "time": 1778259600053,
      "hash": "0x0000000000000000000000000000000000000000000000000000000000000000",
      "delta": {
        "type": "funding",
        "coin": "XRP",
        "usdc": "0.000033",
        "szi": "-41.0",
        "fundingRate": "0.0000005873",
        "nSamples": null
      }
    },
    {
      "time": 1778270400043,
      "hash": "0x0000000000000000000000000000000000000000000000000000000000000000",
      "delta": {
        "type": "funding",
        "coin": "XRP",
        "usdc": "0.000673",
        "szi": "-80.0",
        "fundingRate": "0.000005931",
        "nSamples": null
      }
    },
    {
      "time": 1778274000041,
      "hash": "0x0000000000000000000000000000000000000000000000000000000000000000",
      "delta": {
        "type": "funding",
        "coin": "XRP",
        "usdc": "0.000194",
        "szi": "-11.0",
        "fundingRate": "0.0000125",
        "nSamples": null
      }
    },
    {
      "time": 1778277600054,
      "hash": "0x0000000000000000000000000000000000000000000000000000000000000000",
      "delta": {
        "type": "funding",
        "coin": "XRP",
        "usdc": "0.000142",
        "szi": "-8.0",
        "fundingRate": "0.0000125",
        "nSamples": null
      }
    },
    {
      "time": 1778346000001,
      "hash": "0x0000000000000000000000000000000000000000000000000000000000000000",
      "delta": {
        "type": "funding",
        "coin": "XRP",
        "usdc": "-0.000094",
        "szi": "8.0",
        "fundingRate": "0.0000082998",
        "nSamples": null
      }
    },
    {
      "time": 1778349600017,
      "hash": "0x0000000000000000000000000000000000000000000000000000000000000000",
      "delta": {
        "type": "funding",
        "coin": "XRP",
        "usdc": "-0.000138",
        "szi": "8.0",
        "fundingRate": "0.000012138",
        "nSamples": null
      }
    },
    {
      "time": 1778353200018,
      "hash": "0x0000000000000000000000000000000000000000000000000000000000000000",
      "delta": {
        "type": "funding",
        "coin": "XRP",
        "usdc": "-0.000111",
        "szi": "8.0",
        "fundingRate": "0.0000097992",
        "nSamples": null
      }
    },
    {
      "time": 1778356800068,
      "hash": "0x0000000000000000000000000000000000000000000000000000000000000000",
      "delta": {
        "type": "funding",
        "coin": "XRP",
        "usdc": "-0.000082",
        "szi": "8.0",
        "fundingRate": "0.0000072131",
        "nSamples": null
      }
    },
    {
      "time": 1778360400051,
      "hash": "0x0000000000000000000000000000000000000000000000000000000000000000",
      "delta": {
        "type": "funding",
        "coin": "XRP",
        "usdc": "-0.000142",
        "szi": "8.0",
        "fundingRate": "0.0000125",
        "nSamples": null
      }
    },
    {
      "time": 1778364000008,
      "hash": "0x0000000000000000000000000000000000000000000000000000000000000000",
      "delta": {
        "type": "funding",
        "coin": "XRP",
        "usdc": "-0.000142",
        "szi": "8.0",
        "fundingRate": "0.0000125",
        "nSamples": null
      }
    },
    {
      "time": 1778367600025,
      "hash": "0x0000000000000000000000000000000000000000000000000000000000000000",
      "delta": {
        "type": "funding",
        "coin": "XRP",
        "usdc": "-0.000142",
        "szi": "8.0",
        "fundingRate": "0.0000125",
        "nSamples": null
      }
    },
    {
      "time": 1778371200032,
      "hash": "0x0000000000000000000000000000000000000000000000000000000000000000",
      "delta": {
        "type": "funding",
        "coin": "XRP",
        "usdc": "-0.000142",
        "szi": "8.0",
        "fundingRate": "0.0000125",
        "nSamples": null
      }
    },
    {
      "time": 1778374800048,
      "hash": "0x0000000000000000000000000000000000000000000000000000000000000000",
      "delta": {
        "type": "funding",
        "coin": "XRP",
        "usdc": "-0.000137",
        "szi": "8.0",
        "fundingRate": "0.0000121161",
        "nSamples": null
      }
    },
    {
      "time": 1778378400005,
      "hash": "0x0000000000000000000000000000000000000000000000000000000000000000",
      "delta": {
        "type": "funding",
        "coin": "XRP",
        "usdc": "-0.000113",
        "szi": "8.0",
        "fundingRate": "0.0000100067",
        "nSamples": null
      }
    },
    {
      "time": 1778382000065,
      "hash": "0x0000000000000000000000000000000000000000000000000000000000000000",
      "delta": {
        "type": "funding",
        "coin": "XRP",
        "usdc": "-0.000141",
        "szi": "8.0",
        "fundingRate": "0.0000125",
        "nSamples": null
      }
    },
    {
      "time": 1778385600039,
      "hash": "0x0000000000000000000000000000000000000000000000000000000000000000",
      "delta": {
        "type": "funding",
        "coin": "XRP",
        "usdc": "-0.000105",
        "szi": "8.0",
        "fundingRate": "0.0000093326",
        "nSamples": null
      }
    },
    {
      "time": 1778389200002,
      "hash": "0x0000000000000000000000000000000000000000000000000000000000000000",
      "delta": {
        "type": "funding",
        "coin": "XRP",
        "usdc": "-0.000117",
        "szi": "8.0",
        "fundingRate": "0.000010332",
        "nSamples": null
      }
    },
    {
      "time": 1778392800045,
      "hash": "0x0000000000000000000000000000000000000000000000000000000000000000",
      "delta": {
        "type": "funding",
        "coin": "XRP",
        "usdc": "-0.000132",
        "szi": "8.0",
        "fundingRate": "0.0000117246",
        "nSamples": null
      }
    },
    {
      "time": 1778396400044,
      "hash": "0x0000000000000000000000000000000000000000000000000000000000000000",
      "delta": {
        "type": "funding",
        "coin": "XRP",
        "usdc": "-0.000126",
        "szi": "8.0",
        "fundingRate": "0.0000111404",
        "nSamples": null
      }
    },
    {
      "time": 1778400000015,
      "hash": "0x0000000000000000000000000000000000000000000000000000000000000000",
      "delta": {
        "type": "funding",
        "coin": "XRP",
        "usdc": "-0.000142",
        "szi": "8.0",
        "fundingRate": "0.0000125",
        "nSamples": null
      }
    },
    {
      "time": 1778407200065,
      "hash": "0x0000000000000000000000000000000000000000000000000000000000000000",
      "delta": {
        "type": "funding",
        "coin": "XRP",
        "usdc": "-0.000142",
        "szi": "8.0",
        "fundingRate": "0.0000125",
        "nSamples": null
      }
    },
    {
      "time": 1778443200068,
      "hash": "0x0000000000000000000000000000000000000000000000000000000000000000",
      "delta": {
        "type": "funding",
        "coin": "XRP",
        "usdc": "0.000148",
        "szi": "-8.0",
        "fundingRate": "0.0000125",
        "nSamples": null
      }
    },
    {
      "time": 1778457600028,
      "hash": "0x0000000000000000000000000000000000000000000000000000000000000000",
      "delta": {
        "type": "funding",
        "coin": "ETH",
        "usdc": "-0.008151",
        "szi": "0.275",
        "fundingRate": "0.0000125",
        "nSamples": null
      }
    },
    {
      "time": 1778457600028,
      "hash": "0x0000000000000000000000000000000000000000000000000000000000000000",
      "delta": {
        "type": "funding",
        "coin": "XRP",
        "usdc": "0.000368",
        "szi": "-20.0",
        "fundingRate": "0.0000125",
        "nSamples": null
      }
    },
    {
      "time": 1778461200001,
      "hash": "0x0000000000000000000000000000000000000000000000000000000000000000",
      "delta": {
        "type": "funding",
        "coin": "XRP",
        "usdc": "0.000364",
        "szi": "-20.0",
        "fundingRate": "0.0000125",
        "nSamples": null
      }
    }
  ]
}